[
  {
    "date": "2024-11-18",
    "start": "2024-11-18T08:00:00+00:00",
    "end": "2024-11-18T16:00:00+00:00",
    "value": 1,
    "summary": "The Startup Project",
    "description": "Type: Tutorial\n\nCourse code: 6314MA021Y\n\nStaff member(s): Kuijken, dr. B.\n\nGroup(s): Group 1\n\nCoaching sessions (2 teams, 1 hour)\n\nLocation: REC Impact Event Space\n\nSize: 12\n\nStudy guide: https://studiegids.uva.nl/xmlpages/plspub/redirect?studiegidsnummer=6314MA021Y&jaar=2024-2025\n\nThis appointment is managed by MyTimetable.\n\nLast synchronised on 2025-02-06 at 02:20 CET",
    "calendar_name": "University of Amsterdam - Personal timetable: 13597698@uva.nl",
    "new_date": "2024-11-18",
    "new_start": "2024-11-18T08:00:00+00:00",
    "new_end": "2024-11-18T16:00:00+00:00",
    "id": "79fc486796d1ceb8afe371b1b8901d81ec8a0db17333a928d9693f040eed81e6",
    "version_id": "e51689ece977732491fd6bdfa3cc283332e55df7ebaa61c96d33706c5f2472b6",
    "status": "new"
  },
  {
    "date": "2024-11-19",
    "start": "2024-11-19T08:00:00+00:00",
    "end": "2024-11-19T16:00:00+00:00",
    "value": 1,
    "summary": "The Startup Project",
    "description": "Type: Tutorial\n\nCourse code: 6314MA021Y\n\nStaff member(s): Kuijken, dr. B.\n\nGroup(s): Group 1\n\nCoaching sessions (2 teams, 1 hour)\n\nLocation: REC Impact Event Space\n\nSize: 12\n\nStudy guide: https://studiegids.uva.nl/xmlpages/plspub/redirect?studiegidsnummer=6314MA021Y&jaar=2024-2025\n\nThis appointment is managed by MyTimetable.\n\nLast synchronised on 2025-02-06 at 02:20 CET",
    "calendar_name": "University of Amsterdam - Personal timetable: 13597698@uva.nl",
    "new_date": "2024-11-19",
    "new_start": "2024-11-19T08:00:00+00:00",
    "new_end": "2024-11-19T16:00:00+00:00",
    "id": "017ea6e0a6bd97f3d73161605273421ad9c5383d468f82b58e0516a827b47eaf",
    "version_id": "a81a6fc88b65261e30cd5bc6eeaaba2c5059f736df1a80f2dfe0171b9d1e6682",
    "status": "new"
  },
  {
    "date": "2024-11-20",
    "start": "2024-11-20T10:00:00+00:00",
    "end": "2024-11-20T12:00:00+00:00",
    "value": 1,
    "summary": "Entrepreneurship in Science & Technology",
    "description": "Type: Lecture\n\nCourse code: 6314MA008Y\n\nLocation(s):\nREC E0.04: https://rooster.uva.nl/entity?type=location&key=331%20E0.04&source=2024\n\nStaff member(s): De Cuyper, L.M.C.\n\nSize: 35\n\nStudy guide: https://studiegids.uva.nl/xmlpages/plspub/redirect?studiegidsnummer=6314MA008Y&jaar=2024-2025\n\nThis appointment is managed by MyTimetable.\n\nLast synchronised on 2025-02-06 at 02:20 CET",
    "calendar_name": "University of Amsterdam - Personal timetable: 13597698@uva.nl",
    "new_date": "2024-11-20",
    "new_start": "2024-11-20T10:00:00+00:00",
    "new_end": "2024-11-20T12:00:00+00:00",
    "id": "a8eb14b84ffc5aa92ce91b48cbe004b5ab9e88003a46c334300b66661d68ad4b",
    "version_id": "b069e24626466b880f20a9c6db30bf48e2c7e8bd70e59df521ce6e864f5a2034",
    "status": "new"
  },
  {
    "date": "2024-11-25",
    "start": "2024-11-25T08:00:00+00:00",
    "end": "2024-11-25T16:00:00+00:00",
    "value": 1,
    "summary": "The Startup Project",
    "description": "Type: Presentation\n\nCourse code: 6314MA021Y\n\nStaff member(s): Kuijken, dr. B.\n\nProgress pitch time\n\nLocation: REC Impact Event Space\n\nSize: 130\n\nStudy guide: https://studiegids.uva.nl/xmlpages/plspub/redirect?studiegidsnummer=6314MA021Y&jaar=2024-2025\n\nThis appointment is managed by MyTimetable.\n\nLast synchronised on 2025-02-06 at 02:20 CET",
    "calendar_name": "University of Amsterdam - Personal timetable: 13597698@uva.nl",
    "new_date": "2024-11-25",
    "new_start": "2024-11-25T08:00:00+00:00",
    "new_end": "2024-11-25T16:00:00+00:00",
    "id": "c7e564a23f1c623d534ef7cf533422b784f28e1f6acf06910ef05a45e7ef2178",
    "version_id": "6fa336d5f6d998d2f87f46d1a61e43af65f7907fb54df340033a8c8f5a2f9695",
    "status": "new"
  },
  {
    "date": "2024-11-27",
    "start": "2024-11-27T10:00:00+00:00",
    "end": "2024-11-27T12:00:00+00:00",
    "value": 1,
    "summary": "Entrepreneurship in Science & Technology",
    "description": "Type: Lecture\n\nCourse code: 6314MA008Y\n\nLocation(s):\nREC E0.04: https://rooster.uva.nl/entity?type=location&key=331%20E0.04&source=2024\n\nStaff member(s): De Cuyper, L.M.C.\n\nSize: 35\n\nStudy guide: https://studiegids.uva.nl/xmlpages/plspub/redirect?studiegidsnummer=6314MA008Y&jaar=2024-2025\n\nThis appointment is managed by MyTimetable.\n\nLast synchronised on 2025-02-06 at 02:20 CET",
    "calendar_name": "University of Amsterdam - Personal timetable: 13597698@uva.nl",
    "new_date": "2024-11-27",
    "new_start": "2024-11-27T10:00:00+00:00",
    "new_end": "2024-11-27T12:00:00+00:00",
    "id": "0b4bcf4c893b1ec480cc39ab5f1930fb84d4197f30b4247c279a4955a1a9c1f2",
    "version_id": "2c15ae80f1be3fd6db3a3b65408ce38bba67a445cbf4f7a586161ed2e4b592e1",
    "status": "new"
  },
  {
    "date": "2024-11-27",
    "start": "2024-11-27T14:15:00+00:00",
    "end": "2024-11-27T16:15:00+00:00",
    "value": 1,
    "summary": "Entrepreneurship in Science & Technology",
    "description": "Type: Tutorial\n\nCourse code: 6314MA008Y\n\nLocation(s):\nREC JKT1.03: https://rooster.uva.nl/entity?type=location&key=341.O%20T1.03&source=2024\n\nStaff member(s): De Cuyper, L.M.C.\n\nGroup 1\n\nSize: 35\n\nStudy guide: https://studiegids.uva.nl/xmlpages/plspub/redirect?studiegidsnummer=6314MA008Y&jaar=2024-2025\n\nThis appointment is managed by MyTimetable.\n\nLast synchronised on 2025-02-06 at 02:20 CET",
    "calendar_name": "University of Amsterdam - Personal timetable: 13597698@uva.nl",
    "new_date": "2024-11-27",
    "new_start": "2024-11-27T14:15:00+00:00",
    "new_end": "2024-11-27T16:15:00+00:00",
    "id": "19ff619b172d74d2742b25ce2372c0071fc4e43ad500a97362ad72490302a319",
    "version_id": "739956e9b8cb3337b7dd3189d8ea6fc9daf28abba1dce009d8748d794cf5c6a4",
    "status": "new"
  },
  {
    "date": "2024-12-02",
    "start": "2024-12-02T08:00:00+00:00",
    "end": "2024-12-02T16:00:00+00:00",
    "value": 1,
    "summary": "The Startup Project",
    "description": "Type: Tutorial\n\nCourse code: 6314MA021Y\n\nStaff member(s): Kuijken, dr. B.\n\nGroup(s): Group 1\n\nCoaching sessions (2 teams, 1 hour)\n\nLocation: REC Impact Event Space\n\nSize: 12\n\nStudy guide: https://studiegids.uva.nl/xmlpages/plspub/redirect?studiegidsnummer=6314MA021Y&jaar=2024-2025\n\nThis appointment is managed by MyTimetable.\n\nLast synchronised on 2025-02-06 at 02:20 CET",
    "calendar_name": "University of Amsterdam - Personal timetable: 13597698@uva.nl",
    "new_date": "2024-12-02",
    "new_start": "2024-12-02T08:00:00+00:00",
    "new_end": "2024-12-02T16:00:00+00:00",
    "id": "7b4a043311f8b6c7b2b4e8cdad596aa11771ca16be3e006556bb3af8cabf3664",
    "version_id": "59f7123d4bc9d22d804dd135192f6468c817c04e8ad87925243aadbc0bb078cd",
    "status": "new"
  },
  {
    "date": "2024-12-03",
    "start": "2024-12-03T08:00:00+00:00",
    "end": "2024-12-03T16:00:00+00:00",
    "value": 1,
    "summary": "The Startup Project",
    "description": "Type: Tutorial\n\nCourse code: 6314MA021Y\n\nStaff member(s): Kuijken, dr. B.\n\nGroup(s): Group 1\n\nCoaching sessions (2 teams, 1 hour)\n\nLocation: REC Impact Event Space\n\nSize: 12\n\nStudy guide: https://studiegids.uva.nl/xmlpages/plspub/redirect?studiegidsnummer=6314MA021Y&jaar=2024-2025\n\nThis appointment is managed by MyTimetable.\n\nLast synchronised on 2025-02-06 at 02:20 CET",
    "calendar_name": "University of Amsterdam - Personal timetable: 13597698@uva.nl",
    "new_date": "2024-12-03",
    "new_start": "2024-12-03T08:00:00+00:00",
    "new_end": "2024-12-03T16:00:00+00:00",
    "id": "12f4821caf0c1c9e0ec4982a2ef1e5105649b7beea617b81cf5850ac4fd62c0d",
    "version_id": "b5482253048ce79e181f8a5be06f4eda583a7636fa3d425f297e5b5c7616085d",
    "status": "new"
  },
  {
    "date": "2024-12-04",
    "start": "2024-12-04T10:00:00+00:00",
    "end": "2024-12-04T12:00:00+00:00",
    "value": 1,
    "summary": "Entrepreneurship in Science & Technology",
    "description": "Type: Lecture\n\nCourse code: 6314MA008Y\n\nLocation(s):\nREC E0.04: https://rooster.uva.nl/entity?type=location&key=331%20E0.04&source=2024\n\nStaff member(s): De Cuyper, L.M.C.\n\nSize: 35\n\nStudy guide: https://studiegids.uva.nl/xmlpages/plspub/redirect?studiegidsnummer=6314MA008Y&jaar=2024-2025\n\nThis appointment is managed by MyTimetable.\n\nLast synchronised on 2025-02-06 at 02:20 CET",
    "calendar_name": "University of Amsterdam - Personal timetable: 13597698@uva.nl",
    "new_date": "2024-12-04",
    "new_start": "2024-12-04T10:00:00+00:00",
    "new_end": "2024-12-04T12:00:00+00:00",
    "id": "17493ba73b943a0f348211dd784071438a76ad5f5c9e958239cf692ef2ea195f",
    "version_id": "019ed046179f70ec816ac5b28b14455af90ba4d21f4c8700474168a21d3e0c56",
    "status": "new"
  },
  {
    "date": "2024-12-05",
    "start": "2024-12-05T09:00:00+00:00",
    "end": "2024-12-05T12:00:00+00:00",
    "value": 1,
    "summary": "Entrepreneurship in Science & Technology",
    "description": "Type: Tutorial\n\nCourse code: 6314MA008Y\n\nLocation(s):\nREC JKB.46: https://rooster.uva.nl/entity?type=location&key=341.O%20B.46&source=2024\n\nStaff member(s): De Cuyper, L.M.C.\n\nGroup 1\n\nSize: 35\n\nStudy guide: https://studiegids.uva.nl/xmlpages/plspub/redirect?studiegidsnummer=6314MA008Y&jaar=2024-2025\n\nThis appointment is managed by MyTimetable.\n\nLast synchronised on 2025-02-06 at 02:20 CET",
    "calendar_name": "University of Amsterdam - Personal timetable: 13597698@uva.nl",
    "new_date": "2024-12-05",
    "new_start": "2024-12-05T09:00:00+00:00",
    "new_end": "2024-12-05T12:00:00+00:00",
    "id": "f6ed3d80ed74f8a75eba6d09107cf5112267b6ca8559f1242706fa2670739aeb",
    "version_id": "f88b72690bbf5cdd48f93cd2792cbe7ac13e73e4702313ea10a241c58b46e407",
    "status": "new"
  },
  {
    "date": "2024-12-18",
    "start": "2024-12-18T11:30:00+00:00",
    "end": "2024-12-18T13:30:00+00:00",
    "value": 1,
    "summary": "The Entrepreneurial Individual",
    "description": "Type: Computer-based resit\n\nCourse code: 6314MA046Y\n\nLocation(s):\nTentamenzaal USC Sporthal 1 Sciencepark: https://rooster.uva.nl/entity?type=location&key=Extern%20BOL%20USC%20Tentamenzaal%201&source=2024\n\nStaff member(s): Obschonka, prof. dr. M.\n\nSize: 25\n\nStudy guide: https://studiegids.uva.nl/xmlpages/plspub/redirect?studiegidsnummer=6314MA046Y&jaar=2024-2025\n\nThis appointment is managed by MyTimetable.\n\nLast synchronised on 2025-02-06 at 02:20 CET",
    "calendar_name": "University of Amsterdam - Personal timetable: 13597698@uva.nl",
    "new_date": "2024-12-18",
    "new_start": "2024-12-18T11:30:00+00:00",
    "new_end": "2024-12-18T13:30:00+00:00",
    "id": "8f3b473fa7098eff436c9b2091d6124c0d6b73876b081a08817875cf678183bf",
    "version_id": "c3ad8f117fb5839b019735ce355ac789bf93102812e4c7a1189cbbd04ee249d2",
    "status": "new"
  },
  {
    "date": "2024-12-20",
    "start": "2024-12-20T07:00:00+00:00",
    "end": "2024-12-20T08:00:00+00:00",
    "value": 1,
    "summary": "Entrepreneurship in Science & Technology",
    "description": "Type: Examination\n\nCourse code: 6314MA008Y\n\nStaff member(s): De Cuyper, L.M.C.\n\nSize: 35\n\nStudy guide: https://studiegids.uva.nl/xmlpages/plspub/redirect?studiegidsnummer=6314MA008Y&jaar=2024-2025\n\nThis appointment is managed by MyTimetable.\n\nLast synchronised on 2025-02-06 at 02:20 CET",
    "calendar_name": "University of Amsterdam - Personal timetable: 13597698@uva.nl",
    "new_date": "2024-12-20",
    "new_start": "2024-12-20T07:00:00+00:00",
    "new_end": "2024-12-20T08:00:00+00:00",
    "id": "083748c932d5bb6253db40a240bf3170a182bc5cf3d7aadab6b0552d4905d4c9",
    "version_id": "2e6c92c7d41bba0d077534f11a6ccaebfdbae339031b056446d00714cbd24e4a",
    "status": "new"
  },
  {
    "date": "2024-12-20",
    "start": "2024-12-20T07:00:00+00:00",
    "end": "2024-12-20T08:00:00+00:00",
    "value": 1,
    "summary": "The Startup Project",
    "description": "Type: Examination\n\nCourse code: 6314MA021Y\n\nStaff member(s): Kuijken, dr. B.\n\nDEADLINE\n\nSize: 80\n\nStudy guide: https://studiegids.uva.nl/xmlpages/plspub/redirect?studiegidsnummer=6314MA021Y&jaar=2024-2025\n\nThis appointment is managed by MyTimetable.\n\nLast synchronised on 2025-02-06 at 02:20 CET",
    "calendar_name": "University of Amsterdam - Personal timetable: 13597698@uva.nl",
    "new_date": "2024-12-20",
    "new_start": "2024-12-20T07:00:00+00:00",
    "new_end": "2024-12-20T08:00:00+00:00",
    "id": "f27882de2cf01bbbe514b80db49858d22e6624403dffc162bede4f4ca61f3aa8",
    "version_id": "629c6f59d380f53bc5e6850c3fb4ef1422cf24752c54b0262107acd92d0ea6a2",
    "status": "new"
  },
  {
    "date": "2025-01-06",
    "start": "2025-01-06T08:00:00+00:00",
    "end": "2025-01-06T16:00:00+00:00",
    "value": 1,
    "summary": "Venture Challenge",
    "description": "Type: Tutorial\n\nCourse code: 6314MA044Y\n\nStaff member(s): Kuijken, dr. B.\n\nGroup(s): Group 1\n\nCoaching sessions (2 teams, 1 hour)\n\nWorkshops\n\nSize: 12\n\nStudy guide: https://studiegids.uva.nl/xmlpages/plspub/redirect?studiegidsnummer=6314MA044Y&jaar=2024-2025\n\nThis appointment is managed by MyTimetable.\n\nLast synchronised on 2025-02-06 at 02:20 CET",
    "calendar_name": "University of Amsterdam - Personal timetable: 13597698@uva.nl",
    "new_date": "2025-01-06",
    "new_start": "2025-01-06T08:00:00+00:00",
    "new_end": "2025-01-06T16:00:00+00:00",
    "id": "4b2ed162079648785429ab71c6c4f583c27512b7a5cd129f1786ba0bad97bd82",
    "version_id": "e16023f21c33c20b671e60e79e53c15abf379ae2019dc0eb53d45ed86d8540a5",
    "status": "new"
  },
  {
    "date": "2025-01-07",
    "start": "2025-01-07T08:00:00+00:00",
    "end": "2025-01-07T16:00:00+00:00",
    "value": 1,
    "summary": "Venture Challenge",
    "description": "Type: Tutorial\n\nCourse code: 6314MA044Y\n\nStaff member(s): Kuijken, dr. B.\n\nGroup(s): Group 1\n\nCoaching sessions (2 teams, 1 hour)\n\nWorkshops\n\nSize: 12\n\nStudy guide: https://studiegids.uva.nl/xmlpages/plspub/redirect?studiegidsnummer=6314MA044Y&jaar=2024-2025\n\nThis appointment is managed by MyTimetable.\n\nLast synchronised on 2025-02-06 at 02:20 CET",
    "calendar_name": "University of Amsterdam - Personal timetable: 13597698@uva.nl",
    "new_date": "2025-01-07",
    "new_start": "2025-01-07T08:00:00+00:00",
    "new_end": "2025-01-07T16:00:00+00:00",
    "id": "455358e031cddab6aa794c4a6dc07b8c3b1f4adf19a8805e816427736a4b4a3d",
    "version_id": "9ecf8bbc541b56156cec7dbaa5137466cb7faeada919152bbba96c238ce3e5e7",
    "status": "new"
  },
  {
    "date": "2025-01-13",
    "start": "2025-01-13T00:00:00+00:00",
    "end": "2025-01-14T00:00:00+00:00",
    "value": 1,
    "summary": "Pitch Deck for the pitch event (only for the finalists) [6314MA021Y]",
    "description": "Type: Canvas\n\nThis appointment is managed by MyTimetable.\n\nLast synchronised on 2025-02-06 at 02:20 CET",
    "calendar_name": "University of Amsterdam - Personal timetable: 13597698@uva.nl",
    "new_date": "2025-01-13",
    "new_start": "2025-01-13T00:00:00+00:00",
    "new_end": "2025-01-14T00:00:00+00:00",
    "id": "28d2e61dd6c5c106ae2c0aced01577b643b6f97cb7dc9b9ff2289872f2ca5cf7",
    "version_id": "7e683d40a64f018805403ad0c04c00ebda5cdafcfe75767bbeda58fb39b98b51",
    "status": "new"
  },
  {
    "date": "2025-01-13",
    "start": "2025-01-13T08:00:00+00:00",
    "end": "2025-01-13T16:00:00+00:00",
    "value": 1,
    "summary": "Venture Challenge",
    "description": "Type: Tutorial\n\nCourse code: 6314MA044Y\n\nStaff member(s): Kuijken, dr. B.\n\nGroup(s): Group 1\n\nCoaching sessions (2 teams, 1 hour)\n\nWorkshops\n\nSize: 12\n\nStudy guide: https://studiegids.uva.nl/xmlpages/plspub/redirect?studiegidsnummer=6314MA044Y&jaar=2024-2025\n\nThis appointment is managed by MyTimetable.\n\nLast synchronised on 2025-02-06 at 02:20 CET",
    "calendar_name": "University of Amsterdam - Personal timetable: 13597698@uva.nl",
    "new_date": "2025-01-13",
    "new_start": "2025-01-13T08:00:00+00:00",
    "new_end": "2025-01-13T16:00:00+00:00",
    "id": "5822d746ddff7b104534010b1cbb825531925c09a84de7872acd3473cb6cc5e6",
    "version_id": "fabce70cf34fb72a9e5a0fcfe6be472fd3549e1f14aaf198a3e9248ced1ee5a1",
    "status": "new"
  },
  {
    "date": "2025-01-14",
    "start": "2025-01-14T08:00:00+00:00",
    "end": "2025-01-14T16:00:00+00:00",
    "value": 1,
    "summary": "Venture Challenge",
    "description": "Type: Tutorial\n\nCourse code: 6314MA044Y\n\nStaff member(s): Kuijken, dr. B.\n\nGroup(s): Group 1\n\nCoaching sessions (2 teams, 1 hour)\n\nWorkshops\n\nSize: 12\n\nStudy guide: https://studiegids.uva.nl/xmlpages/plspub/redirect?studiegidsnummer=6314MA044Y&jaar=2024-2025\n\nThis appointment is managed by MyTimetable.\n\nLast synchronised on 2025-02-06 at 02:20 CET",
    "calendar_name": "University of Amsterdam - Personal timetable: 13597698@uva.nl",
    "new_date": "2025-01-14",
    "new_start": "2025-01-14T08:00:00+00:00",
    "new_end": "2025-01-14T16:00:00+00:00",
    "id": "e71ad5086d70b7f178930f7c494eb32b03a992e3111f6792bbac4e20d3adf5bd",
    "version_id": "61220feed314e01a581d0800753987c2af216781b55560ac61d1c97d87f92f21",
    "status": "new"
  },
  {
    "date": "2025-01-16",
    "start": "2025-01-16T15:00:00+00:00",
    "end": "2025-01-16T18:00:00+00:00",
    "value": 1,
    "summary": "The Startup Project",
    "description": "Type: Presentation\n\nCourse code: 6314MA021Y\n\nStaff member(s): Kuijken, dr. B.\n\nPitch Finals\n\nLocation: REC Impact Event Space\n\nSize: 80\n\nStudy guide: https://studiegids.uva.nl/xmlpages/plspub/redirect?studiegidsnummer=6314MA021Y&jaar=2024-2025\n\nThis appointment is managed by MyTimetable.\n\nLast synchronised on 2025-02-06 at 02:20 CET",
    "calendar_name": "University of Amsterdam - Personal timetable: 13597698@uva.nl",
    "new_date": "2025-01-16",
    "new_start": "2025-01-16T15:00:00+00:00",
    "new_end": "2025-01-16T18:00:00+00:00",
    "id": "4fe37f69d60ef65bcfced7c1e2c00915853ced130c0a4d43bb925877b2f72854",
    "version_id": "13badf33e1c16f7fb159776b2c928f35e42f14c63aba98d287c20338aba845d5",
    "status": "new"
  },
  {
    "date": "2025-01-17",
    "start": "2025-01-17T00:00:00+00:00",
    "end": "2025-01-18T00:00:00+00:00",
    "value": 1,
    "summary": "Progress Update (individual assignment) [6314MA044Y]",
    "description": "Type: Canvas\n\nThis appointment is managed by MyTimetable.\n\nLast synchronised on 2025-02-06 at 02:20 CET",
    "calendar_name": "University of Amsterdam - Personal timetable: 13597698@uva.nl",
    "new_date": "2025-01-17",
    "new_start": "2025-01-17T00:00:00+00:00",
    "new_end": "2025-01-18T00:00:00+00:00",
    "id": "e3a9fa20edf579207c6f58509f6a5710c38e4e152ec931f8e91b5f07904e50ee",
    "version_id": "a8a9f42891ace1454f272a8ab9bea56b21a7c9370c774dbe5021b377a8f0703b",
    "status": "new"
  },
  {
    "date": "2025-01-20",
    "start": "2025-01-20T08:00:00+00:00",
    "end": "2025-01-20T16:00:00+00:00",
    "value": 1,
    "summary": "Venture Challenge",
    "description": "Type: Tutorial\n\nCourse code: 6314MA044Y\n\nStaff member(s): Kuijken, dr. B.\n\nGroup(s): Group 1\n\nCoaching sessions (2 teams, 1 hour)\n\nWorkshops\n\nSize: 12\n\nStudy guide: https://studiegids.uva.nl/xmlpages/plspub/redirect?studiegidsnummer=6314MA044Y&jaar=2024-2025\n\nThis appointment is managed by MyTimetable.\n\nLast synchronised on 2025-02-06 at 02:20 CET",
    "calendar_name": "University of Amsterdam - Personal timetable: 13597698@uva.nl",
    "new_date": "2025-01-20",
    "new_start": "2025-01-20T08:00:00+00:00",
    "new_end": "2025-01-20T16:00:00+00:00",
    "id": "35957cd4447c9adffb15d3e1b8c824546200ca5b120870c8c72c5162ea714ced",
    "version_id": "df3373b1ccffbba282b136fa645de48c3074d9e90a4429b15735c1d438846c7e",
    "status": "new"
  },
  {
    "date": "2025-01-21",
    "start": "2025-01-21T08:00:00+00:00",
    "end": "2025-01-21T16:00:00+00:00",
    "value": 1,
    "summary": "Venture Challenge",
    "description": "Type: Tutorial\n\nCourse code: 6314MA044Y\n\nStaff member(s): Kuijken, dr. B.\n\nGroup(s): Group 1\n\nCoaching sessions (2 teams, 1 hour)\n\nWorkshops\n\nSize: 12\n\nStudy guide: https://studiegids.uva.nl/xmlpages/plspub/redirect?studiegidsnummer=6314MA044Y&jaar=2024-2025\n\nThis appointment is managed by MyTimetable.\n\nLast synchronised on 2025-02-06 at 02:20 CET",
    "calendar_name": "University of Amsterdam - Personal timetable: 13597698@uva.nl",
    "new_date": "2025-01-21",
    "new_start": "2025-01-21T08:00:00+00:00",
    "new_end": "2025-01-21T16:00:00+00:00",
    "id": "2c4521b97059ef412c6b34fe1e2d70d62a33ee053e07843c0f2d392acc83c8a4",
    "version_id": "e48cbfa0841f441e8cad244b3bd7f3d79bdccd8aa21cd8e9afe34bf710515704",
    "status": "new"
  },
  {
    "date": "2025-01-27",
    "start": "2025-01-27T08:00:00+00:00",
    "end": "2025-01-27T16:00:00+00:00",
    "value": 1,
    "summary": "Venture Challenge",
    "description": "Type: Presentation\n\nCourse code: 6314MA044Y\n\nStaff member(s): Kuijken, dr. B.\n\nGroup(s): Group 1\n\nFinal Presentations\n\nLokaal: REC Impact Board Room\n\nSize: 12\n\nStudy guide: https://studiegids.uva.nl/xmlpages/plspub/redirect?studiegidsnummer=6314MA044Y&jaar=2024-2025\n\nThis appointment is managed by MyTimetable.\n\nLast synchronised on 2025-02-06 at 02:20 CET",
    "calendar_name": "University of Amsterdam - Personal timetable: 13597698@uva.nl",
    "new_date": "2025-01-27",
    "new_start": "2025-01-27T08:00:00+00:00",
    "new_end": "2025-01-27T16:00:00+00:00",
    "id": "252a317e39ffdf49a0b00ff789356f76a914a36784e67f3f34e1d12875bdebae",
    "version_id": "5cac60bfd12a3202ddaf2fd5741ac8dea3cb9ed166130131a98397858df76533",
    "status": "new"
  },
  {
    "date": "2025-01-27",
    "start": "2025-01-27T10:00:00+00:00",
    "end": "2025-01-27T11:00:00+00:00",
    "value": 1,
    "summary": "The Startup Project",
    "description": "Type: Resit\n\nCourse code: 6314MA021Y\n\nStaff member(s): Kuijken, dr. B.\n\nLocation: REC Impact Event Space\n\nSize: 80\n\nStudy guide: https://studiegids.uva.nl/xmlpages/plspub/redirect?studiegidsnummer=6314MA021Y&jaar=2024-2025\n\nThis appointment is managed by MyTimetable.\n\nLast synchronised on 2025-02-06 at 02:20 CET",
    "calendar_name": "University of Amsterdam - Personal timetable: 13597698@uva.nl",
    "new_date": "2025-01-27",
    "new_start": "2025-01-27T10:00:00+00:00",
    "new_end": "2025-01-27T11:00:00+00:00",
    "id": "1501be4deb69d14061e7267ded493ce4d6b00aa6c3d01f25607ebee1a0349ac6",
    "version_id": "705a1f27fe528e034c8afa189a8fa0cd0f3837f0973426905b020d165663fe95",
    "status": "new"
  },
  {
    "date": "2025-01-28",
    "start": "2025-01-28T08:00:00+00:00",
    "end": "2025-01-28T16:00:00+00:00",
    "value": 1,
    "summary": "Venture Challenge",
    "description": "Type: Presentation\n\nCourse code: 6314MA044Y\n\nStaff member(s): Kuijken, dr. B.\n\nGroup(s): Group 1\n\nFinal Presentations\n\nLokaal: REC Impact Board Room\n\nSize: 12\n\nStudy guide: https://studiegids.uva.nl/xmlpages/plspub/redirect?studiegidsnummer=6314MA044Y&jaar=2024-2025\n\nThis appointment is managed by MyTimetable.\n\nLast synchronised on 2025-02-06 at 02:20 CET",
    "calendar_name": "University of Amsterdam - Personal timetable: 13597698@uva.nl",
    "new_date": "2025-01-28",
    "new_start": "2025-01-28T08:00:00+00:00",
    "new_end": "2025-01-28T16:00:00+00:00",
    "id": "8a2153114b815128dd76167b58f5c2f4ac51cbe5d90155c4f4992e488e6b5c42",
    "version_id": "8243be4407a4ab5f6d02706d0384e897afca558f03271796e0f0eb444ad0475b",
    "status": "new"
  },
  {
    "date": "2025-01-31",
    "start": "2025-01-31T00:00:00+00:00",
    "end": "2025-02-01T00:00:00+00:00",
    "value": 1,
    "summary": "Report, blogpost, and presentation [6314MA044Y]",
    "description": "Type: Canvas\n\nThis appointment is managed by MyTimetable.\n\nLast synchronised on 2025-02-06 at 02:20 CET",
    "calendar_name": "University of Amsterdam - Personal timetable: 13597698@uva.nl",
    "new_date": "2025-01-31",
    "new_start": "2025-01-31T00:00:00+00:00",
    "new_end": "2025-02-01T00:00:00+00:00",
    "id": "09977e8bd15fdb40343e87293ac8911aa2f24dbdd96629b053d91365476fdb50",
    "version_id": "0dd2aa8f73667efac13423ca39005929c184419ebc00e8939680ff32b455f00f",
    "status": "new"
  },
  {
    "date": "2025-01-31",
    "start": "2025-01-31T00:00:00+00:00",
    "end": "2025-02-01T00:00:00+00:00",
    "value": 1,
    "summary": "Share distribution (only one team member should submit this) [6314MA044Y]",
    "description": "Type: Canvas\n\nThis appointment is managed by MyTimetable.\n\nLast synchronised on 2025-02-06 at 02:20 CET",
    "calendar_name": "University of Amsterdam - Personal timetable: 13597698@uva.nl",
    "new_date": "2025-01-31",
    "new_start": "2025-01-31T00:00:00+00:00",
    "new_end": "2025-02-01T00:00:00+00:00",
    "id": "ad888121444281893155c9baafe56bc202d2adc71743133b21cfc5ba0b64c0e9",
    "version_id": "c047abf4f4b081c3f68ad72c7fe9dd8ac76446862e9a0ab832a724bb4dd00a6b",
    "status": "new"
  },
  {
    "date": "2025-01-31",
    "start": "2025-01-31T07:00:00+00:00",
    "end": "2025-01-31T08:00:00+00:00",
    "value": 1,
    "summary": "Entrepreneurship in Science & Technology",
    "description": "Type: Resit\n\nCourse code: 6314MA008Y\n\nStaff member(s): De Cuyper, L.M.C.\n\nSize: 35\n\nStudy guide: https://studiegids.uva.nl/xmlpages/plspub/redirect?studiegidsnummer=6314MA008Y&jaar=2024-2025\n\nThis appointment is managed by MyTimetable.\n\nLast synchronised on 2025-02-06 at 02:20 CET",
    "calendar_name": "University of Amsterdam - Personal timetable: 13597698@uva.nl",
    "new_date": "2025-01-31",
    "new_start": "2025-01-31T07:00:00+00:00",
    "new_end": "2025-01-31T08:00:00+00:00",
    "id": "5ec9113d8c1cc60beaf33d3b554b66da0a4b254594a1b73f8ac20329a28be82f",
    "version_id": "faca124891de399d61812b8a5f1d7a97e800b71da4ab69231c7b637c495c3517",
    "status": "new"
  },
  {
    "date": "2025-01-31",
    "start": "2025-01-31T08:00:00+00:00",
    "end": "2025-01-31T09:00:00+00:00",
    "value": 1,
    "summary": "Venture Challenge",
    "description": "Type: Resit\n\nCourse code: 6314MA044Y\n\nStaff member(s): Kuijken, dr. B.\n\nDEADLINE\n\nRetake\n\nSize: 0\n\nStudy guide: https://studiegids.uva.nl/xmlpages/plspub/redirect?studiegidsnummer=6314MA044Y&jaar=2024-2025\n\nThis appointment is managed by MyTimetable.\n\nLast synchronised on 2025-02-06 at 02:20 CET",
    "calendar_name": "University of Amsterdam - Personal timetable: 13597698@uva.nl",
    "new_date": "2025-01-31",
    "new_start": "2025-01-31T08:00:00+00:00",
    "new_end": "2025-01-31T09:00:00+00:00",
    "id": "641d84725fc08d51336eeb05e121bc182d13a8c85f1b75ea4b833b3efde65db8",
    "version_id": "4fddd4d1ad0a699158518a864cbf30d753354aab89ccdb7d4b3d73e60271156a",
    "status": "new"
  }
]