[{"date":"2025-06-18T00:00:00.000","start":"2025-06-18T07:30:00+00:00","end":"2025-06-18T14:00:00+00:00","value":1.0,"summary":"workl","description":"(No description)","calendar_name":"Work creative clicks","new_date":"2025-06-18","new_start":"2025-06-18T07:30:00+00:00","new_end":"2025-06-18T14:00:00+00:00","id":"159d0ce779fe1158c03acaef4a1d4e28380ebae21c49fd9c059cd0e56f72e374","version_id":"09a8ecf627aa426f335ec3041f32f4f91d07f45d4f845e01a9d420ed955de014","status":"unchanged","duration":390.0,"deleted":false},{"date":"2025-06-19T00:00:00.000","start":"2025-06-19T06:00:00+00:00","end":"2025-06-19T07:15:00+00:00","value":1.0,"summary":"gym","description":"(No description)","calendar_name":"Fitness","new_date":"2025-06-19","new_start":"2025-06-19T06:00:00+00:00","new_end":"2025-06-19T07:15:00+00:00","id":"a2efad901728150b88b6f8fa3ad5bab85c772f479b261d39f204c379531d6452","version_id":"35c10b8c31bf64147a4be97b2817a310da140da3c65956d033678a34964ec4b4","status":"unchanged","duration":75.0,"deleted":false},{"date":"2025-06-22T00:00:00.000","start":"2025-06-22T11:00:00+00:00","end":"2025-06-22T13:00:00+00:00","value":1.0,"summary":"football","description":"(No description)","calendar_name":"Fitness","new_date":"2025-06-22","new_start":"2025-06-22T11:00:00+00:00","new_end":"2025-06-22T13:00:00+00:00","id":"7c2bbd035c86ed3efc2e5537e6acf79274ee40732d8dcec26777ebeb8722bf16","version_id":"0dc8ce8dc313cae5fa5eb7beb2b7c5e06b94f78206fa37e1c4366abb9ebe9542","status":"unchanged","duration":120.0,"deleted":false},{"date":"2025-06-18T00:00:00.000","start":"2025-06-18T06:00:00+00:00","end":"2025-06-18T07:00:00+00:00","value":1.0,"summary":"Forough Zarea's Zoom Meeting","description":"Please join zoom on your booked time slots. There is a waiting room. Please wait till I let you in. I will be notified that you are in the waiting room but might not have finished with the previous student.\n\n\n Hi there,\nForough Zarea is inviting you to a scheduled Zoom meeting.\n\nJoin Zoom Meeting\nhttps:\/\/qut.zoom.us\/j\/84078591052?pwd=rmgs0lvgOpZ2aRqHUZaPwYRsjnb8Hh.1&from=addon\n\nMeeting ID: 840 7859 1052\nPasscode: 181210\n\n---\n\nOne tap mobile\n+61861193900,,84078591052#,,,,*181210# Australia\n+61871501149,,84078591052#,,,,*181210# Australia\n\n---\n\nDial by your location\n\u2022 +61 8 6119 3900 Australia\n\u2022 +61 8 7150 1149 Australia\n\u2022 +61 2 8015 6011 Australia\n\u2022 +61 3 7018 2005 Australia\n\u2022 +61 7 3185 3730 Australia\n\nMeeting ID: 840 7859 1052\nPasscode: 181210\n\nFind your local number: https:\/\/qut.zoom.us\/u\/kboVMilKu5\n\n---\n\nJoin by SIP or H.323\n84078591052@global.zoomcrc.com<mailto:84078591052@global.zoomcrc.com>\n\nMeeting ID: 840 7859 1052\nPasscode: 181210\n","calendar_name":"jonkuhar11@gmail.com","new_date":"2025-06-18","new_start":"2025-06-18T06:00:00+00:00","new_end":"2025-06-18T07:00:00+00:00","id":"c248b9c8e19aba5b565cceecf2b141911639eb9d9ede076ee4eecfd38a9f19c8","version_id":"988c5975bf4ae797341f88127db9ce552a0be67ef6176b7c5dfd5c21ae121987","status":"unchanged","duration":60.0,"deleted":false},{"date":"2025-06-19T00:00:00.000","start":"2025-06-19T08:00:00+00:00","end":"2025-06-19T09:15:00+00:00","value":1.0,"summary":"packing everything","description":"(No description)","calendar_name":"jonkuhar11@gmail.com","new_date":"2025-06-19","new_start":"2025-06-19T08:00:00+00:00","new_end":"2025-06-19T09:15:00+00:00","id":"baadf4c06f84322b1c325e782a8dc2cd79b18105f62af30948ed48fa572140ad","version_id":"a3447c31d9ff0a09859ec421394ebee57c2e4d8bd7bdc396b863af9a370151f8","status":"unchanged","duration":75.0,"deleted":false},{"date":"2025-06-19T00:00:00.000","start":"2025-06-19T09:30:00+00:00","end":"2025-06-19T13:15:00+00:00","value":1.0,"summary":"cleaning everything","description":"(No description)","calendar_name":"jonkuhar11@gmail.com","new_date":"2025-06-19","new_start":"2025-06-19T09:30:00+00:00","new_end":"2025-06-19T13:15:00+00:00","id":"5f8f439957e6d8c78fc3209288aca77fcd79486dd44c24c1d2e453e35cf81f8e","version_id":"55ba3021b5ca6b0ce7c9f4964e3264522d9b2acd87dce5f0d69abf24a16fa4a2","status":"unchanged","duration":225.0,"deleted":false},{"date":"2025-06-19T00:00:00.000","start":"2025-06-19T15:10:00+00:00","end":"2025-06-19T15:50:00+00:00","value":1.0,"summary":"Appointment","description":"To see detailed information for automatically created events like this one, use the official Google Calendar app. https:\/\/g.co\/calendar\n\nThis event was created from an email you received in Gmail. https:\/\/mail.google.com\/mail?extsrc=cal&plid=ACUX6DMsAr9N4lf3z3AvHC2aLJ3OicppbbhWxyU\n","calendar_name":"jonkuhar11@gmail.com","new_date":"2025-06-19","new_start":"2025-06-19T15:10:00+00:00","new_end":"2025-06-19T15:50:00+00:00","id":"863203d00dbae326150c35ec6a63c0a804a58ef436a6403867df95dfc38f6d07","version_id":"fc34fad2211ea2a38bbcabc3e43d2005e42c4ae99efa81713c9a55cd51457b2f","status":"unchanged","duration":40.0,"deleted":false},{"date":"2025-06-20T00:00:00.000","start":"2025-06-20T04:30:00+00:00","end":"2025-06-20T06:15:00+00:00","value":1.0,"summary":"Flight to Ljubljana (HV 6819)","description":"To see detailed information for automatically created events like this one, use the official Google Calendar app. https:\/\/g.co\/calendar\n\nThis event was created from an email you received in Gmail. https:\/\/mail.google.com\/mail?extsrc=cal&plid=ACUX6DNEuqHADQudHhEIewFlmDRHiUfSM1QiXRg\n","calendar_name":"jonkuhar11@gmail.com","new_date":"2025-06-20","new_start":"2025-06-20T04:30:00+00:00","new_end":"2025-06-20T06:15:00+00:00","id":"77c099499ad4fd0214aba4ffe19801b3b639b4f37159bd9aab600ba43922f365","version_id":"24d020fad04ac05eb54f25aaac9b99aa76115f36e2e19478d596227fbef1ddb1","status":"unchanged","duration":105.0,"deleted":false},{"date":"2025-06-22T00:00:00.000","start":"2025-06-22T02:30:00+00:00","end":"2025-06-22T02:45:00+00:00","value":1.0,"summary":"Weekly check up of goals NOTION","description":"(No description)","calendar_name":"jonkuhar11@gmail.com","new_date":"2025-06-22","new_start":"2025-06-22T02:30:00+00:00","new_end":"2025-06-22T02:45:00+00:00","id":"25ca297661def32b0bce0a13012a2bec6c8f0d28a26a35ea5b62f8dd646db429","version_id":"8e31aa9e50effc4e3bc9f9a3c3b55fadbaea137c87dec3661eba3ee1d0ae6421","status":"unchanged","duration":15.0,"deleted":false}]